[
  [
    {
      "category": "roster",
      "rows": [
        {
          "href": "https://www.pro-football-reference.com/players/A/AndrDa00.htm",
          "player": "David Andrews",
          "age": "32",
          "pos": "C",
          "g": "1",
          "gs": "1",
          "weight": "300",
          "height": "6-2",
          "college_id": "Georgia",
          "birth_date_mod": "7/10/1992",
          "experience": "9",
          "av": "",
          "draft_info": ""
        },
        {
          "href": "https://www.pro-football-reference.com/players/A/AustAl00.htm",
          "player": "Alex Austin",
          "age": "23",
          "pos": "CB",
          "g": "1",
          "gs": "0",
          "weight": "191",
          "height": "",
          "college_id": "Oregon St.",
          "birth_date_mod": "5/22/2001",
          "experience": "1",
          "av": "",
          "draft_info": "Buffalo Bills / 7th / 252nd pick / 2023"
        },
        {
          "href": "https://www.pro-football-reference.com/players/B/BakeJa00.htm",
          "player": "Javon Baker",
          "age": "22",
          "pos": "WR",
          "g": "0",
          "gs": "0",
          "weight": "202",
          "height": "",
          "college_id": "Alabama,Central Florida",
          "birth_date_mod": "2/18/2002",
          "experience": "Rook",
          "av": "",
          "draft_info": "New England Patriots / 4th / 110th pick / 2024"
        },
        {
          "href": "https://www.pro-football-reference.com/players/B/BariBr00.htm",
          "player": "Bryce Baringer",
          "age": "25",
          "pos": "P",
          "g": "1",
          "gs": "0",
          "weight": "215",
          "height": "6-2",
          "college_id": "Michigan St.",
          "birth_date_mod": "4/26/1999",
          "experience": "1",
          "av": "",
          "draft_info": "New England Patriots / 6th / 192nd pick / 2023"
        },
        {
          "href": "https://www.pro-football-reference.com/players/B/BellJa00.htm",
          "player": "Jaheim Bell",
          "age": "23",
          "pos": "TE",
          "g": "1",
          "gs": "0",
          "weight": "241",
          "height": "",
          "college_id": "South Carolina,Florida St.",
          "birth_date_mod": "6/14/2001",
          "experience": "Rook",
          "av": "",
          "draft_info": "New England Patriots / 7th / 231st pick / 2024"
        },
        {
          "href": "https://www.pro-football-reference.com/players/B/BentJa00.htm",
          "player": "Ja'Whaun Bentley",
          "age": "28",
          "pos": "LB",
          "g": "1",
          "gs": "1",
          "weight": "250",
          "height": "6-2",
          "college_id": "Purdue",
          "birth_date_mod": "8/24/1996",
          "experience": "6",
          "av": "",
          "draft_info": "New England Patriots / 5th / 143rd pick / 2018"
        },
        {
          "href": "https://www.pro-football-reference.com/players/B/BoutKa00.htm",
          "player": "Kayshon Boutte",
          "age": "22",
          "pos": "WR",
          "g": "0",
          "gs": "0",
          "weight": "197",
          "height": "5-11",
          "college_id": "LSU",
          "birth_date_mod": "5/7/2002",
          "experience": "1",
          "av": "",
          "draft_info": "New England Patriots / 6th / 187th pick / 2023"
        },
        {
          "href": "https://www.pro-football-reference.com/players/B/BrisJa00.htm",
          "player": "Jacoby Brissett",
          "age": "32",
          "pos": "QB",
          "g": "1",
          "gs": "1",
          "weight": "235",
          "height": "6-4",
          "college_id": "Florida,North Carolina St.",
          "birth_date_mod": "12/11/1992",
          "experience": "8",
          "av": "",
          "draft_info": "New England Patriots / 3rd / 91st pick / 2016"
        },
        {
          "href": "https://www.pro-football-reference.com/players/C/CardJo00.htm",
          "player": "Joe Cardona",
          "age": "32",
          "pos": "LS",
          "g": "1",
          "gs": "0",
          "weight": "245",
          "height": "6-2",
          "college_id": "Navy",
          "birth_date_mod": "4/16/1992",
          "experience": "9",
          "av": "",
          "draft_info": "New England Patriots / 5th / 166th pick / 2015"
        },
        {
          "href": "https://www.pro-football-reference.com/players/D/DialMa00.htm",
          "player": "Marcellas Dial",
          "age": "24",
          "pos": "DB",
          "g": "1",
          "gs": "0",
          "weight": "190",
          "height": "",
          "college_id": "Georgia Military,South Carolina",
          "birth_date_mod": "12/6/2000",
          "experience": "Rook",
          "av": "",
          "draft_info": "New England Patriots / 6th / 180th pick / 2024"
        },
        {
          "href": "https://www.pro-football-reference.com/players/D/DougDe00.htm",
          "player": "Demario Douglas",
          "age": "24",
          "pos": "WR",
          "g": "1",
          "gs": "1",
          "weight": "192",
          "height": "",
          "college_id": "Liberty",
          "birth_date_mod": "12/8/2000",
          "experience": "1",
          "av": "",
          "draft_info": "New England Patriots / 6th / 210th pick / 2023"
        },
        {
          "href": "https://www.pro-football-reference.com/players/D/DuggKy00.htm",
          "player": "Kyle Dugger",
          "age": "28",
          "pos": "S",
          "g": "1",
          "gs": "1",
          "weight": "216",
          "height": "6-1",
          "college_id": "Lenoir-Rhyne",
          "birth_date_mod": "3/22/1996",
          "experience": "4",
          "av": "",
          "draft_info": "New England Patriots / 2nd / 37th pick / 2020"
        },
        {
          "href": "https://www.pro-football-reference.com/players/E/EkuaDa00.htm",
          "player": "Daniel Ekuale",
          "age": "30",
          "pos": "DT",
          "g": "1",
          "gs": "1",
          "weight": "310",
          "height": "6-3",
          "college_id": "Washington St.",
          "birth_date_mod": "1/13/1994",
          "experience": "5",
          "av": "",
          "draft_info": ""
        },
        {
          "href": "https://www.pro-football-reference.com/players/E/ElliCh00.htm",
          "player": "Christian Elliss",
          "age": "25",
          "pos": "LB",
          "g": "1",
          "gs": "0",
          "weight": "231",
          "height": "6-2",
          "college_id": "Idaho",
          "birth_date_mod": "1/2/1999",
          "experience": "3",
          "av": "",
          "draft_info": ""
        },
        {
          "href": "https://www.pro-football-reference.com/players/G/GibsAn00.htm",
          "player": "Antonio Gibson",
          "age": "26",
          "pos": "RB",
          "g": "1",
          "gs": "0",
          "weight": "228",
          "height": "6-0",
          "college_id": "East Central CC (MS),Memphis",
          "birth_date_mod": "6/23/1998",
          "experience": "4",
          "av": "",
          "draft_info": "Washington Football Team / 3rd / 66th pick / 2020"
        },
        {
          "href": "https://www.pro-football-reference.com/players/G/GodcDa00.htm",
          "player": "Davon Godchaux",
          "age": "30",
          "pos": "DT",
          "g": "1",
          "gs": "1",
          "weight": "330",
          "height": "6-3",
          "college_id": "LSU",
          "birth_date_mod": "11/11/1994",
          "experience": "7",
          "av": "",
          "draft_info": "Miami Dolphins / 5th / 178th pick / 2017"
        },
        {
          "href": "https://www.pro-football-reference.com/players/G/GonzCh00.htm",
          "player": "Christian Gonzalez",
          "age": "22",
          "pos": "CB",
          "g": "1",
          "gs": "1",
          "weight": "205",
          "height": "6-1",
          "college_id": "Colorado,Oregon",
          "birth_date_mod": "6/28/2002",
          "experience": "1",
          "av": "",
          "draft_info": "New England Patriots / 1st / 17th pick / 2023"
        },
        {
          "href": "https://www.pro-football-reference.com/players/H/HastJa02.htm",
          "player": "Jamycal Hasty",
          "age": "28",
          "pos": "RB",
          "g": "1",
          "gs": "0",
          "weight": "205",
          "height": "5-8",
          "college_id": "Baylor",
          "birth_date_mod": "9/12/1996",
          "experience": "4",
          "av": "",
          "draft_info": ""
        },
        {
          "href": "https://www.pro-football-reference.com/players/H/HawkJa00.htm",
          "player": "Jaylinn Hawkins",
          "age": "27",
          "pos": "S",
          "g": "1",
          "gs": "0",
          "weight": "208",
          "height": "6-1",
          "college_id": "California",
          "birth_date_mod": "8/25/1997",
          "experience": "4",
          "av": "",
          "draft_info": "Atlanta Falcons / 4th / 134th pick / 2020"
        },
        {
          "href": "https://www.pro-football-reference.com/players/H/HenrHu00.htm",
          "player": "Hunter Henry",
          "age": "30",
          "pos": "TE",
          "g": "1",
          "gs": "1",
          "weight": "249",
          "height": "6-5",
          "college_id": "Arkansas",
          "birth_date_mod": "12/7/1994",
          "experience": "8",
          "av": "",
          "draft_info": "San Diego Chargers / 2nd / 35th pick / 2016"
        },
        {
          "href": "https://www.pro-football-reference.com/players/H/HoopAu00.htm",
          "player": "Austin Hooper",
          "age": "30",
          "pos": "TE",
          "g": "1",
          "gs": "0",
          "weight": "254",
          "height": "6-4",
          "college_id": "Stanford",
          "birth_date_mod": "10/29/1994",
          "experience": "8",
          "av": "",
          "draft_info": "Atlanta Falcons / 3rd / 81st pick / 2016"
        },
        {
          "href": "https://www.pro-football-reference.com/players/J/JacoCu00.htm",
          "player": "Curtis Jacobs",
          "age": "",
          "pos": "LB",
          "g": "0",
          "gs": "0",
          "weight": "241",
          "height": "",
          "college_id": "Penn St.",
          "birth_date_mod": "",
          "experience": "Rook",
          "av": "",
          "draft_info": ""
        },
        {
          "href": "https://www.pro-football-reference.com/players/J/JacoDe00.htm",
          "player": "Demontrey Jacobs",
          "age": "26",
          "pos": "OT",
          "g": "0",
          "gs": "0",
          "weight": "315",
          "height": "6-6",
          "college_id": "South Florida",
          "birth_date_mod": "11/22/1998",
          "experience": "Rook",
          "av": "",
          "draft_info": ""
        },
        {
          "href": "https://www.pro-football-reference.com/players/J/JennAn00.htm",
          "player": "Anfernee Jennings",
          "age": "27",
          "pos": "LB",
          "g": "1",
          "gs": "1",
          "weight": "255",
          "height": "6-2",
          "college_id": "Alabama",
          "birth_date_mod": "9/1/1997",
          "experience": "4",
          "av": "",
          "draft_info": "New England Patriots / 3rd / 87th pick / 2020"
        },
        {
          "href": "https://www.pro-football-reference.com/players/J/JohnEr01.htm",
          "player": "Eric Johnson",
          "age": "26",
          "pos": "DT",
          "g": "0",
          "gs": "0",
          "weight": "299",
          "height": "6-4",
          "college_id": "Missouri State",
          "birth_date_mod": "7/16/1998",
          "experience": "2",
          "av": "",
          "draft_info": "Indianapolis Colts / 5th / 159th pick / 2022"
        },
        {
          "href": "https://www.pro-football-reference.com/players/J/JoneJo03.htm",
          "player": "Jonathan Jones",
          "age": "31",
          "pos": "CB",
          "g": "1",
          "gs": "1",
          "weight": "185",
          "height": "5-9",
          "college_id": "Auburn",
          "birth_date_mod": "9/20/1993",
          "experience": "8",
          "av": "",
          "draft_info": ""
        },
        {
          "href": "https://www.pro-football-reference.com/players/J/JoneMa06.htm",
          "player": "Marcus Jones",
          "age": "26",
          "pos": "CB",
          "g": "1",
          "gs": "1",
          "weight": "188",
          "height": "5-8",
          "college_id": "Troy,Houston",
          "birth_date_mod": "10/22/1998",
          "experience": "2",
          "av": "",
          "draft_info": "New England Patriots / 3rd / 85th pick / 2022"
        },
        {
          "href": "https://www.pro-football-reference.com/players/L/LeveNi00.htm",
          "player": "Nick Leverett",
          "age": "27",
          "pos": "G",
          "g": "1",
          "gs": "0",
          "weight": "310",
          "height": "6-3",
          "college_id": "Rice",
          "birth_date_mod": "1/11/1997",
          "experience": "3",
          "av": "",
          "draft_info": ""
        },
        {
          "href": "https://www.pro-football-reference.com/players/L/LoweVe00.htm",
          "player": "Vederian Lowe",
          "age": "25",
          "pos": "T",
          "g": "1",
          "gs": "0",
          "weight": "315",
          "height": "6-5",
          "college_id": "Illinois",
          "birth_date_mod": "4/17/1999",
          "experience": "2",
          "av": "",
          "draft_info": "Minnesota Vikings / 6th / 184th pick / 2022"
        },
        {
          "href": "https://www.pro-football-reference.com/players/M/MayeDr00.htm",
          "player": "Drake Maye",
          "age": "22",
          "pos": "QB",
          "g": "0",
          "gs": "0",
          "weight": "225",
          "height": "",
          "college_id": "North Carolina",
          "birth_date_mod": "8/30/2002",
          "experience": "Rook",
          "av": "",
          "draft_info": "New England Patriots / 1st / 3rd pick / 2024"
        },
        {
          "href": "https://www.pro-football-reference.com/players/M/McMiRa02.htm",
          "player": "Raekwon McMillan",
          "age": "28",
          "pos": "LB",
          "g": "1",
          "gs": "0",
          "weight": "250",
          "height": "6-2",
          "college_id": "Ohio St.",
          "birth_date_mod": "11/17/1996",
          "experience": "6",
          "av": "",
          "draft_info": "Miami Dolphins / 2nd / 54th pick / 2017"
        },
        {
          "href": "https://www.pro-football-reference.com/players/M/MiltJo00.htm",
          "player": "Joe Milton",
          "age": "24",
          "pos": "QB",
          "g": "0",
          "gs": "0",
          "weight": "246",
          "height": "",
          "college_id": "Michigan,Tennessee",
          "birth_date_mod": "3/6/2000",
          "experience": "Rook",
          "av": "",
          "draft_info": "New England Patriots / 6th / 193rd pick / 2024"
        },
        {
          "href": "https://www.pro-football-reference.com/players/O/OkorCh00.htm",
          "player": "Chukwuma Okorafor",
          "age": "27",
          "pos": "T",
          "g": "1",
          "gs": "1",
          "weight": "320",
          "height": "6-6",
          "college_id": "Western Michigan",
          "birth_date_mod": "8/8/1997",
          "experience": "6",
          "av": "",
          "draft_info": "Pittsburgh Steelers / 3rd / 92nd pick / 2018"
        },
        {
          "href": "https://www.pro-football-reference.com/players/O/OnweMi00.htm",
          "player": "Michael Onwenu",
          "age": "27",
          "pos": "OL",
          "g": "1",
          "gs": "1",
          "weight": "350",
          "height": "6-3",
          "college_id": "Michigan",
          "birth_date_mod": "12/10/1997",
          "experience": "4",
          "av": "",
          "draft_info": "New England Patriots / 6th / 182nd pick / 2020"
        },
        {
          "href": "https://www.pro-football-reference.com/players/O/OsboKJ00.htm",
          "player": "K.J. Osborn",
          "age": "27",
          "pos": "WR",
          "g": "1",
          "gs": "1",
          "weight": "200",
          "height": "6-0",
          "college_id": "Buffalo,Miami (FL)",
          "birth_date_mod": "6/10/1997",
          "experience": "4",
          "av": "",
          "draft_info": "Minnesota Vikings / 5th / 176th pick / 2020"
        },
        {
          "href": "https://www.pro-football-reference.com/players/P/PeppJa00.htm",
          "player": "Jabrill Peppers",
          "age": "29",
          "pos": "S",
          "g": "1",
          "gs": "1",
          "weight": "217",
          "height": "5-11",
          "college_id": "Michigan",
          "birth_date_mod": "10/4/1995",
          "experience": "7",
          "av": "",
          "draft_info": "Cleveland Browns / 1st / 25th pick / 2017"
        },
        {
          "href": "https://www.pro-football-reference.com/players/P/PettDe00.htm",
          "player": "Dell Pettus",
          "age": "23",
          "pos": "S",
          "g": "1",
          "gs": "0",
          "weight": "200",
          "height": "5-11",
          "college_id": "Troy",
          "birth_date_mod": "6/2/2001",
          "experience": "Rook",
          "av": "",
          "draft_info": ""
        },
        {
          "href": "https://www.pro-football-reference.com/players/P/PharJe00.htm",
          "player": "Jeremiah Pharms",
          "age": "28",
          "pos": "DT",
          "g": "1",
          "gs": "0",
          "weight": "300",
          "height": "6-2",
          "college_id": "Sacramento CC,Delta College,Friends",
          "birth_date_mod": "10/16/1996",
          "experience": "1",
          "av": "",
          "draft_info": ""
        },
        {
          "href": "https://www.pro-football-reference.com/players/P/PolkJa00.htm",
          "player": "Ja'Lynn Polk",
          "age": "22",
          "pos": "WR",
          "g": "1",
          "gs": "0",
          "weight": "203",
          "height": "",
          "college_id": "Texas Tech,Washington",
          "birth_date_mod": "4/11/2002",
          "experience": "Rook",
          "av": "",
          "draft_info": "New England Patriots / 2nd / 37th pick / 2024"
        },
        {
          "href": "https://www.pro-football-reference.com/players/R/RobiLa02.htm",
          "player": "Layden Robinson",
          "age": "23",
          "pos": "G",
          "g": "1",
          "gs": "1",
          "weight": "311",
          "height": "6-3",
          "college_id": "Texas A&M",
          "birth_date_mod": "5/3/2001",
          "experience": "Rook",
          "av": "",
          "draft_info": "New England Patriots / 4th / 103rd pick / 2024"
        },
        {
          "href": "https://www.pro-football-reference.com/players/S/SchoBr00.htm",
          "player": "Brenden Schooler",
          "age": "27",
          "pos": "S",
          "g": "1",
          "gs": "0",
          "weight": "210",
          "height": "6-2",
          "college_id": "Oregon,Texas",
          "birth_date_mod": "5/30/1997",
          "experience": "2",
          "av": "",
          "draft_info": ""
        },
        {
          "href": "https://www.pro-football-reference.com/players/S/SlyeJo00.htm",
          "player": "Joey Slye",
          "age": "28",
          "pos": "K",
          "g": "1",
          "gs": "0",
          "weight": "213",
          "height": "5-11",
          "college_id": "Virginia Tech",
          "birth_date_mod": "4/10/1996",
          "experience": "5",
          "av": "",
          "draft_info": ""
        },
        {
          "href": "https://www.pro-football-reference.com/players/S/SowxSi00.htm",
          "player": "Sidy Sow",
          "age": "26",
          "pos": "G",
          "g": "0",
          "gs": "0",
          "weight": "318",
          "height": "6-5",
          "college_id": "Eastern Michigan",
          "birth_date_mod": "6/28/1998",
          "experience": "1",
          "av": "",
          "draft_info": "New England Patriots / 4th / 117th pick / 2023"
        },
        {
          "href": "https://www.pro-football-reference.com/players/S/StevRh00.htm",
          "player": "Rhamondre Stevenson",
          "age": "26",
          "pos": "RB",
          "g": "1",
          "gs": "1",
          "weight": "227",
          "height": "6-0",
          "college_id": "Cerritos (CA),Oklahoma",
          "birth_date_mod": "2/23/1998",
          "experience": "3",
          "av": "",
          "draft_info": "New England Patriots / 4th / 120th pick / 2021"
        },
        {
          "href": "https://www.pro-football-reference.com/players/T/TavaJa00.htm",
          "player": "Jahlani Tavai",
          "age": "28",
          "pos": "LB",
          "g": "1",
          "gs": "1",
          "weight": "255",
          "height": "6-2",
          "college_id": "Hawaii",
          "birth_date_mod": "9/28/1996",
          "experience": "5",
          "av": "",
          "draft_info": "Detroit Lions / 2nd / 43rd pick / 2019"
        },
        {
          "href": "https://www.pro-football-reference.com/players/T/ThomZa04.htm",
          "player": "Zachary Thomas",
          "age": "26",
          "pos": "OT",
          "g": "0",
          "gs": "0",
          "weight": "305",
          "height": "6-5",
          "college_id": "San Diego St.",
          "birth_date_mod": "5/26/1998",
          "experience": "2",
          "av": "",
          "draft_info": "Chicago Bears / 6th / 186th pick / 2022"
        },
        {
          "href": "https://www.pro-football-reference.com/players/T/ThorTy00.htm",
          "player": "Tyquan Thornton",
          "age": "24",
          "pos": "WR",
          "g": "1",
          "gs": "1",
          "weight": "185",
          "height": "6-2",
          "college_id": "Baylor",
          "birth_date_mod": "9/7/2000",
          "experience": "2",
          "av": "",
          "draft_info": "New England Patriots / 2nd / 50th pick / 2022"
        },
        {
          "href": "https://www.pro-football-reference.com/players/U/UcheJo00.htm",
          "player": "Josh Uche",
          "age": "26",
          "pos": "LB",
          "g": "1",
          "gs": "0",
          "weight": "240",
          "height": "6-1",
          "college_id": "Michigan",
          "birth_date_mod": "9/18/1998",
          "experience": "4",
          "av": "",
          "draft_info": "New England Patriots / 2nd / 60th pick / 2020"
        },
        {
          "href": "https://www.pro-football-reference.com/players/W/WallCa00.htm",
          "player": "Caedan Wallace",
          "age": "24",
          "pos": "T",
          "g": "1",
          "gs": "0",
          "weight": "314",
          "height": "",
          "college_id": "Penn St.",
          "birth_date_mod": "4/18/2000",
          "experience": "Rook",
          "av": "",
          "draft_info": "New England Patriots / 3rd / 68th pick / 2024"
        },
        {
          "href": "https://www.pro-football-reference.com/players/W/WhitKe03.htm",
          "player": "Keion White",
          "age": "25",
          "pos": "DE",
          "g": "1",
          "gs": "1",
          "weight": "285",
          "height": "6-5",
          "college_id": "Old Dominion,Georgia Tech",
          "birth_date_mod": "1/20/1999",
          "experience": "1",
          "av": "",
          "draft_info": "New England Patriots / 2nd / 46th pick / 2023"
        },
        {
          "href": "https://www.pro-football-reference.com/players/W/WilsMa04.htm",
          "player": "Marco Wilson",
          "age": "25",
          "pos": "CB",
          "g": "1",
          "gs": "0",
          "weight": "191",
          "height": "6-0",
          "college_id": "Florida",
          "birth_date_mod": "3/3/1999",
          "experience": "3",
          "av": "",
          "draft_info": "Arizona Cardinals / 4th / 136th pick / 2021"
        },
        {
          "href": "https://www.pro-football-reference.com/players/W/WiseDe00.htm",
          "player": "Deatrich Wise Jr.",
          "age": "30",
          "pos": "DE",
          "g": "1",
          "gs": "0",
          "weight": "280",
          "height": "6-5",
          "college_id": "Arkansas",
          "birth_date_mod": "7/26/1994",
          "experience": "7",
          "av": "",
          "draft_info": "New England Patriots / 4th / 131st pick / 2017"
        },
        {
          "href": "https://www.pro-football-reference.com/players/X/XimiOs00.htm",
          "player": "Oshane Ximines",
          "age": "28",
          "pos": "OLB",
          "g": "1",
          "gs": "0",
          "weight": "254",
          "height": "6-4",
          "college_id": "Old Dominion",
          "birth_date_mod": "12/7/1996",
          "experience": "5",
          "av": "",
          "draft_info": "New York Giants / 3rd / 95th pick / 2019"
        },
        {
          "href": "https://www.pro-football-reference.com/players/B/BourKe00.htm",
          "player": "Kendrick Bourne (PUP)",
          "age": "29",
          "pos": "WR",
          "g": "0",
          "gs": "0",
          "weight": "205",
          "height": "6-1",
          "college_id": "Eastern Washington",
          "birth_date_mod": "8/4/1995",
          "experience": "7",
          "av": "",
          "draft_info": ""
        },
        {
          "href": "https://www.pro-football-reference.com/players/S/StraCo01.htm",
          "player": "Cole Strange (PUP)",
          "age": "26",
          "pos": "G",
          "g": "0",
          "gs": "0",
          "weight": "310",
          "height": "6-5",
          "college_id": "Chattanooga",
          "birth_date_mod": "7/31/1998",
          "experience": "2",
          "av": "",
          "draft_info": "New England Patriots / 1st / 29th pick / 2022"
        },
        {
          "href": "https://www.pro-football-reference.com/players/T/TakiSi00.htm",
          "player": "Sione Takitaki (PUP)",
          "age": "29",
          "pos": "LB",
          "g": "0",
          "gs": "0",
          "weight": "245",
          "height": "6-1",
          "college_id": "BYU",
          "birth_date_mod": "6/8/1995",
          "experience": "5",
          "av": "",
          "draft_info": "Cleveland Browns / 3rd / 80th pick / 2019"
        },
        {
          "href": "https://www.pro-football-reference.com/players/B/BarmCh00.htm",
          "player": "Christian Barmore (NON)",
          "age": "25",
          "pos": "DT",
          "g": "0",
          "gs": "0",
          "weight": "315",
          "height": "6-5",
          "college_id": "Alabama",
          "birth_date_mod": "7/28/1999",
          "experience": "3",
          "av": "",
          "draft_info": "New England Patriots / 2nd / 38th pick / 2021"
        },
        {
          "href": "https://www.pro-football-reference.com/players/M/MapuMa00.htm",
          "player": "Marte Mapu (IRD)",
          "age": "25",
          "pos": "S",
          "g": "0",
          "gs": "0",
          "weight": "230",
          "height": "6-3",
          "college_id": "Sacramento St.",
          "birth_date_mod": "11/8/1999",
          "experience": "1",
          "av": "",
          "draft_info": "New England Patriots / 3rd / 76th pick / 2023"
        },
        {
          "href": "https://www.pro-football-reference.com/players/A/AndrJa00.htm",
          "player": "Jake Andrews (IR)",
          "age": "25",
          "pos": "C",
          "g": "0",
          "gs": "0",
          "weight": "308",
          "height": "",
          "college_id": "Troy",
          "birth_date_mod": "11/11/1999",
          "experience": "1",
          "av": "",
          "draft_info": "New England Patriots / 4th / 107th pick / 2023"
        },
        {
          "href": "https://www.pro-football-reference.com/players/J/JackJa03.htm",
          "player": "JaQuae Jackson (IR)",
          "age": "24",
          "pos": "WR",
          "g": "0",
          "gs": "0",
          "weight": "184",
          "height": "6-1",
          "college_id": "Rutgers",
          "birth_date_mod": "1/30/2000",
          "experience": "Rook",
          "av": "",
          "draft_info": ""
        },
        {
          "href": "https://www.pro-football-reference.com/players/W/WattAr01.htm",
          "player": "Armon Watts (IR)",
          "age": "28",
          "pos": "DT",
          "g": "0",
          "gs": "0",
          "weight": "307",
          "height": "6-5",
          "college_id": "Arkansas",
          "birth_date_mod": "7/22/1996",
          "experience": "5",
          "av": "",
          "draft_info": "Minnesota Vikings / 6th / 190th pick / 2019"
        },
        {
          "href": "https://www.pro-football-reference.com/players/W/WheaTy01.htm",
          "player": "Tyrone Wheatley Jr. (IR)",
          "age": "27",
          "pos": "T",
          "g": "0",
          "gs": "0",
          "weight": "320",
          "height": "6-6",
          "college_id": "Michigan,Stony Brook",
          "birth_date_mod": "2/4/1997",
          "experience": "1",
          "av": "",
          "draft_info": ""
        }
      ]
    }
  ]
]