[{"category":"passing","rows":[]},{"category":"advanced_air_yards","rows":[]},{"category":"advanced_accuracy","rows":[]},{"category":"advanced_pressure","rows":[]},{"category":"advanced_play_tape","rows":[]},{"category":"passing_advanced","rows":[]},{"category":"fantasy","rows":[]},{"category":"detailed_receiving_and_rushing","rows":[]},{"category":"receiving_and_rushing","rows":[]},{"category":"rushing_and_receiving","rows":[]},{"category":"detailed_rushing_and_receiving","rows":[]},{"category":"defense","rows":[{"year_id":"2023","age":"24","team":"KAN","pos":"LB","uniform_number":"44","g":"17","gs":"1","def_int":"","def_int_yds":"","def_int_td":"0","def_int_long":"","pass_defended":"","fumbles_forced":"0","fumbles":"0","fumbles_rec":"0","fumbles_rec_yds":"0","fumbles_rec_td":"0","sacks":"0.0","tackles_combined":"17","tackles_solo":"14","tackles_assists":"3","tackles_loss":"0","qb_hits":"0","safety_md":"","av":"2"}]},{"category":"punting","rows":[]},{"category":"returns","rows":[]},{"category":"scoring","rows":[]},{"category":"snap_counts","rows":[{"year_id":"2023","age":"24","team":"KAN","pos":"LB","uniform_number":"44","g":"17","gs":"1","offense":"0","off_pct":"0%","defense":"81","def_pct":"7%","special_teams":"283","st_pct":"67%"}]},{"category":"stats","rows":[{"game_date":"2023-09-07","game_num":"1","week_num":"1","age":"23.321","team":"KAN","game_location":"","opp":"DET","game_result":"L 20-21","gs":"","sacks":"","tackles_solo":"","tackles_assists":"","tackles_combined":"","tackles_loss":"","qb_hits":"","offense":"0","off_pct":"0%","defense":"0","def_pct":"0%","special_teams":"18","st_pct":"67%","status":""},{"game_date":"2023-09-17","game_num":"2","week_num":"2","age":"23.331","team":"KAN","game_location":"@","opp":"JAX","game_result":"W 17-9","gs":"","sacks":"0.0","tackles_solo":"1","tackles_assists":"0","tackles_combined":"1","tackles_loss":"0","qb_hits":"0","offense":"0","off_pct":"0%","defense":"0","def_pct":"0%","special_teams":"15","st_pct":"68%","status":""},{"game_date":"2023-09-24","game_num":"3","week_num":"3","age":"23.338","team":"KAN","game_location":"","opp":"CHI","game_result":"W 41-10","gs":"","sacks":"","tackles_solo":"","tackles_assists":"","tackles_combined":"","tackles_loss":"","qb_hits":"","offense":"0","off_pct":"0%","defense":"0","def_pct":"0%","special_teams":"16","st_pct":"64%","status":""},{"game_date":"2023-10-01","game_num":"4","week_num":"4","age":"23.345","team":"KAN","game_location":"@","opp":"NYJ","game_result":"W 23-20","gs":"","sacks":"0.0","tackles_solo":"1","tackles_assists":"0","tackles_combined":"1","tackles_loss":"0","qb_hits":"0","offense":"0","off_pct":"0%","defense":"0","def_pct":"0%","special_teams":"17","st_pct":"65%","status":""},{"game_date":"2023-10-08","game_num":"5","week_num":"5","age":"23.352","team":"KAN","game_location":"@","opp":"MIN","game_result":"W 27-20","gs":"","sacks":"","tackles_solo":"","tackles_assists":"","tackles_combined":"","tackles_loss":"","qb_hits":"","offense":"0","off_pct":"0%","defense":"0","def_pct":"0%","special_teams":"14","st_pct":"58%","status":""},{"game_date":"2023-10-12","game_num":"6","week_num":"6","age":"23.356","team":"KAN","game_location":"","opp":"DEN","game_result":"W 19-8","gs":"","sacks":"","tackles_solo":"","tackles_assists":"","tackles_combined":"","tackles_loss":"","qb_hits":"","offense":"0","off_pct":"0%","defense":"0","def_pct":"0%","special_teams":"14","st_pct":"67%","status":""},{"game_date":"2023-10-22","game_num":"7","week_num":"7","age":"24.001","team":"KAN","game_location":"","opp":"LAC","game_result":"W 31-17","gs":"","sacks":"","tackles_solo":"","tackles_assists":"","tackles_combined":"","tackles_loss":"","qb_hits":"","offense":"0","off_pct":"0%","defense":"0","def_pct":"0%","special_teams":"16","st_pct":"62%","status":""},{"game_date":"2023-10-29","game_num":"8","week_num":"8","age":"24.008","team":"KAN","game_location":"@","opp":"DEN","game_result":"L 9-24","gs":"","sacks":"","tackles_solo":"","tackles_assists":"","tackles_combined":"","tackles_loss":"","qb_hits":"","offense":"0","off_pct":"0%","defense":"2","def_pct":"3%","special_teams":"12","st_pct":"54%","status":""},{"game_date":"2023-11-05","game_num":"9","week_num":"9","age":"24.015","team":"KAN","game_location":"","opp":"MIA","game_result":"W 21-14","gs":"","sacks":"0.0","tackles_solo":"0","tackles_assists":"1","tackles_combined":"1","tackles_loss":"0","qb_hits":"0","offense":"0","off_pct":"0%","defense":"0","def_pct":"0%","special_teams":"20","st_pct":"80%","status":""},{"game_date":"2023-11-20","game_num":"10","week_num":"11","age":"24.030","team":"KAN","game_location":"","opp":"PHI","game_result":"L 17-21","gs":"","sacks":"","tackles_solo":"","tackles_assists":"","tackles_combined":"","tackles_loss":"","qb_hits":"","offense":"0","off_pct":"0%","defense":"0","def_pct":"0%","special_teams":"18","st_pct":"69%","status":""},{"game_date":"2023-11-26","game_num":"11","week_num":"12","age":"24.036","team":"KAN","game_location":"@","opp":"LVR","game_result":"W 31-17","gs":"","sacks":"","tackles_solo":"","tackles_assists":"","tackles_combined":"","tackles_loss":"","qb_hits":"","offense":"0","off_pct":"0%","defense":"0","def_pct":"0%","special_teams":"17","st_pct":"65%","status":""},{"game_date":"2023-12-03","game_num":"12","week_num":"13","age":"24.043","team":"KAN","game_location":"@","opp":"GNB","game_result":"L 19-27","gs":"","sacks":"0.0","tackles_solo":"0","tackles_assists":"1","tackles_combined":"1","tackles_loss":"0","qb_hits":"0","offense":"0","off_pct":"0%","defense":"0","def_pct":"0%","special_teams":"13","st_pct":"59%","status":""},{"game_date":"2023-12-10","game_num":"13","week_num":"14","age":"24.050","team":"KAN","game_location":"","opp":"BUF","game_result":"L 17-20","gs":"","sacks":"","tackles_solo":"","tackles_assists":"","tackles_combined":"","tackles_loss":"","qb_hits":"","offense":"0","off_pct":"0%","defense":"0","def_pct":"0%","special_teams":"17","st_pct":"71%","status":""},{"game_date":"2023-12-17","game_num":"14","week_num":"15","age":"24.057","team":"KAN","game_location":"@","opp":"NWE","game_result":"W 27-17","gs":"","sacks":"0.0","tackles_solo":"1","tackles_assists":"0","tackles_combined":"1","tackles_loss":"0","qb_hits":"0","offense":"0","off_pct":"0%","defense":"0","def_pct":"0%","special_teams":"18","st_pct":"60%","status":""},{"game_date":"2023-12-25","game_num":"15","week_num":"16","age":"24.065","team":"KAN","game_location":"","opp":"LVR","game_result":"L 14-20","gs":"","sacks":"","tackles_solo":"","tackles_assists":"","tackles_combined":"","tackles_loss":"","qb_hits":"","offense":"0","off_pct":"0%","defense":"0","def_pct":"0%","special_teams":"19","st_pct":"76%","status":""},{"game_date":"2023-12-31","game_num":"16","week_num":"17","age":"24.071","team":"KAN","game_location":"","opp":"CIN","game_result":"W 25-17","gs":"","sacks":"","tackles_solo":"","tackles_assists":"","tackles_combined":"","tackles_loss":"","qb_hits":"","offense":"0","off_pct":"0%","defense":"0","def_pct":"0%","special_teams":"17","st_pct":"63%","status":""},{"game_date":"2024-01-07","game_num":"17","week_num":"18","age":"24.078","team":"KAN","game_location":"@","opp":"LAC","game_result":"W 13-12","gs":"*","sacks":"0.0","tackles_solo":"11","tackles_assists":"1","tackles_combined":"12","tackles_loss":"0","qb_hits":"0","offense":"0","off_pct":"0%","defense":"79","def_pct":"95%","special_teams":"22","st_pct":"81%","status":""}]}]