[
  {
    "category": "passing",
    "rows": []
  },
  {
    "category": "advanced_air_yards",
    "rows": []
  },
  {
    "category": "advanced_accuracy",
    "rows": []
  },
  {
    "category": "advanced_pressure",
    "rows": []
  },
  {
    "category": "advanced_play_tape",
    "rows": []
  },
  {
    "category": "passing_advanced",
    "rows": []
  },
  {
    "category": "fantasy",
    "rows": []
  },
  {
    "category": "detailed_receiving_and_rushing",
    "rows": []
  },
  {
    "category": "receiving_and_rushing",
    "rows": []
  },
  {
    "category": "rushing_and_receiving",
    "rows": []
  },
  {
    "category": "detailed_rushing_and_receiving",
    "rows": []
  },
  {
    "category": "defense",
    "rows": [
      {
        "year_id": "2022",
        "age": "25",
        "team": "2TM",
        "pos": "DT",
        "uniform_number": "",
        "g": "7",
        "gs": "1",
        "def_int": "",
        "def_int_yds": "",
        "def_int_td": "0",
        "def_int_long": "",
        "pass_defended": "",
        "fumbles_forced": "0",
        "fumbles": "0",
        "fumbles_rec": "0",
        "fumbles_rec_yds": "0",
        "fumbles_rec_td": "0",
        "sacks": "0.0",
        "tackles_combined": "5",
        "tackles_solo": "0",
        "tackles_assists": "5",
        "tackles_loss": "0",
        "qb_hits": "1",
        "safety_md": "",
        "av": "1"
      },
      {
        "year_id": "",
        "age": "",
        "team": "MIA",
        "pos": "DT",
        "uniform_number": "90",
        "g": "1",
        "gs": "0",
        "def_int": "",
        "def_int_yds": "",
        "def_int_td": "0",
        "def_int_long": "",
        "pass_defended": "",
        "fumbles_forced": "0",
        "fumbles": "0",
        "fumbles_rec": "0",
        "fumbles_rec_yds": "0",
        "fumbles_rec_td": "0",
        "sacks": "0.0",
        "tackles_combined": "2",
        "tackles_solo": "0",
        "tackles_assists": "2",
        "tackles_loss": "0",
        "qb_hits": "0",
        "safety_md": "",
        "av": "0"
      },
      {
        "year_id": "",
        "age": "",
        "team": "CLE",
        "pos": "DT",
        "uniform_number": "57",
        "g": "6",
        "gs": "1",
        "def_int": "",
        "def_int_yds": "",
        "def_int_td": "0",
        "def_int_long": "",
        "pass_defended": "",
        "fumbles_forced": "0",
        "fumbles": "0",
        "fumbles_rec": "0",
        "fumbles_rec_yds": "0",
        "fumbles_rec_td": "0",
        "sacks": "0.0",
        "tackles_combined": "3",
        "tackles_solo": "0",
        "tackles_assists": "3",
        "tackles_loss": "0",
        "qb_hits": "1",
        "safety_md": "",
        "av": "1"
      },
      {
        "year_id": "2023",
        "age": "26",
        "team": "ARI",
        "pos": "DL",
        "uniform_number": "90",
        "g": "5",
        "gs": "0",
        "def_int": "",
        "def_int_yds": "",
        "def_int_td": "0",
        "def_int_long": "",
        "pass_defended": "",
        "fumbles_forced": "0",
        "fumbles": "0",
        "fumbles_rec": "0",
        "fumbles_rec_yds": "0",
        "fumbles_rec_td": "0",
        "sacks": "1.0",
        "tackles_combined": "8",
        "tackles_solo": "6",
        "tackles_assists": "2",
        "tackles_loss": "0",
        "qb_hits": "1",
        "safety_md": "",
        "av": "0"
      },
      {
        "year_id": "2024",
        "age": "27",
        "team": "TAM",
        "pos": "DL",
        "uniform_number": "56",
        "g": "1",
        "gs": "0",
        "def_int": "",
        "def_int_yds": "",
        "def_int_td": "0",
        "def_int_long": "",
        "pass_defended": "",
        "fumbles_forced": "0",
        "fumbles": "0",
        "fumbles_rec": "0",
        "fumbles_rec_yds": "0",
        "fumbles_rec_td": "0",
        "sacks": "0.0",
        "tackles_combined": "1",
        "tackles_solo": "0",
        "tackles_assists": "1",
        "tackles_loss": "0",
        "qb_hits": "0",
        "safety_md": "",
        "av": ""
      }
    ]
  },
  {
    "category": "punting",
    "rows": []
  },
  {
    "category": "returns",
    "rows": []
  },
  {
    "category": "scoring",
    "rows": []
  },
  {
    "category": "snap_counts",
    "rows": [
      {
        "year_id": "2022",
        "age": "25",
        "team": "2TM",
        "pos": "DT",
        "uniform_number": "",
        "g": "7",
        "gs": "1",
        "offense": "0",
        "off_pct": "",
        "defense": "84",
        "def_pct": "",
        "special_teams": "1",
        "st_pct": ""
      },
      {
        "year_id": "",
        "age": "",
        "team": "MIA",
        "pos": "DT",
        "uniform_number": "90",
        "g": "1",
        "gs": "0",
        "offense": "0",
        "off_pct": "0%",
        "defense": "9",
        "def_pct": "12%",
        "special_teams": "0",
        "st_pct": "0%"
      },
      {
        "year_id": "",
        "age": "",
        "team": "",
        "pos": "",
        "uniform_number": "",
        "g": "",
        "gs": "",
        "offense": "0",
        "off_pct": "0%",
        "defense": "75",
        "def_pct": "20%",
        "special_teams": "1",
        "st_pct": "1%"
      },
      {
        "year_id": "2023",
        "age": "26",
        "team": "ARI",
        "pos": "DL",
        "uniform_number": "90",
        "g": "5",
        "gs": "0",
        "offense": "0",
        "off_pct": "0%",
        "defense": "134",
        "def_pct": "38%",
        "special_teams": "0",
        "st_pct": "0%"
      },
      {
        "year_id": "2024",
        "age": "27",
        "team": "TAM",
        "pos": "DL",
        "uniform_number": "56",
        "g": "1",
        "gs": "0",
        "offense": "0",
        "off_pct": "0%",
        "defense": "6",
        "def_pct": "10%",
        "special_teams": "0",
        "st_pct": "0%"
      }
    ]
  },
  {
    "name": "Ben Stille",
    "id": "StilBe00",
    "team": "TB",
    "age": "27",
    "position": "DL",
    "weight": "296",
    "height": "6-4",
    "college": "Nebraska",
    "experience": "2",
    "href": "https://www.pro-football-reference.com/players/S/StilBe00.htm"
  }
]