[
  {
    "category": "fantasy",
    "rows": [
      {
        "year_id": "2021",
        "age": "23",
        "g": "11",
        "fantasy_pos": "RB",
        "fantasy_points": "146",
        "vbd": "",
        "fantasy_rank_pos": "24",
        "fantasy_rank_overall": "",
        "games": "All 2021 Games"
      },
      {
        "year_id": "2022",
        "age": "24",
        "g": "5",
        "fantasy_pos": "RB",
        "fantasy_points": "41",
        "vbd": "",
        "fantasy_rank_pos": "69",
        "fantasy_rank_overall": "",
        "games": "All 2022 Games"
      },
      {
        "year_id": "2023",
        "age": "25",
        "g": "11",
        "fantasy_pos": "RB",
        "fantasy_points": "42",
        "vbd": "",
        "fantasy_rank_pos": "64",
        "fantasy_rank_overall": "",
        "games": "All 2023 Games"
      }
    ]
  },
  {
    "category": "detailed_rushing_and_receiving",
    "rows": [
      {
        "year_id": "2021",
        "age": "23",
        "team": "SFO",
        "pos": "RB",
        "uniform_number": "25",
        "g": "11",
        "gs": "10",
        "rush_att": "207",
        "rush_yds": "963",
        "rush_first_down": "47",
        "rush_yds_before_contact": "448",
        "rush_yds_bc_per_rush": "2.2",
        "rush_yac": "515",
        "rush_yac_per_rush": "2.5",
        "rush_broken_tackles": "16",
        "rush_broken_tackles_per_rush": "12.9",
        "targets": "20",
        "rec": "19",
        "rec_yds": "137",
        "rec_first_down": "6",
        "rec_air_yds": "-14",
        "rec_air_yds_per_rec": "-0.7",
        "rec_yac": "151",
        "rec_yac_per_rec": "7.9",
        "rec_adot": "-0.6",
        "rec_broken_tackles": "1",
        "rec_broken_tackles_per_rec": "19.0",
        "rec_drops": "1",
        "rec_drop_pct": "5.0",
        "rec_target_int": "0",
        "rec_pass_rating": "111.9"
      },
      {
        "year_id": "2022",
        "age": "24",
        "team": "SFO",
        "pos": "RB",
        "uniform_number": "25",
        "g": "5",
        "gs": "1",
        "rush_att": "45",
        "rush_yds": "279",
        "rush_first_down": "15",
        "rush_yds_before_contact": "170",
        "rush_yds_bc_per_rush": "3.8",
        "rush_yac": "109",
        "rush_yac_per_rush": "2.4",
        "rush_broken_tackles": "2",
        "rush_broken_tackles_per_rush": "22.5",
        "targets": "4",
        "rec": "3",
        "rec_yds": "7",
        "rec_first_down": "0",
        "rec_air_yds": "-9",
        "rec_air_yds_per_rec": "-3.0",
        "rec_yac": "16",
        "rec_yac_per_rec": "5.3",
        "rec_adot": "-1.8",
        "rec_broken_tackles": "0",
        "rec_broken_tackles_per_rec": "",
        "rec_drops": "0",
        "rec_drop_pct": "0.0",
        "rec_target_int": "0",
        "rec_pass_rating": "77.1"
      },
      {
        "year_id": "2023",
        "age": "25",
        "team": "SFO",
        "pos": "RB",
        "uniform_number": "25",
        "g": "11",
        "gs": "1",
        "rush_att": "75",
        "rush_yds": "281",
        "rush_first_down": "14",
        "rush_yds_before_contact": "138",
        "rush_yds_bc_per_rush": "1.8",
        "rush_yac": "143",
        "rush_yac_per_rush": "1.9",
        "rush_broken_tackles": "6",
        "rush_broken_tackles_per_rush": "12.5",
        "targets": "8",
        "rec": "6",
        "rec_yds": "14",
        "rec_first_down": "2",
        "rec_air_yds": "-12",
        "rec_air_yds_per_rec": "-2.0",
        "rec_yac": "26",
        "rec_yac_per_rec": "4.3",
        "rec_adot": "-2.8",
        "rec_broken_tackles": "0",
        "rec_broken_tackles_per_rec": "",
        "rec_drops": "1",
        "rec_drop_pct": "12.5",
        "rec_target_int": "1",
        "rec_pass_rating": "37.5"
      }
    ]
  },
  {
    "category": "passing",
    "rows": []
  },
  {
    "category": "advanced_air_yards",
    "rows": []
  },
  {
    "category": "advanced_accuracy",
    "rows": []
  },
  {
    "category": "advanced_pressure",
    "rows": []
  },
  {
    "category": "advanced_play_tape",
    "rows": []
  },
  {
    "category": "passing_advanced",
    "rows": []
  },
  {
    "category": "detailed_receiving_and_rushing",
    "rows": []
  },
  {
    "category": "receiving_and_rushing",
    "rows": []
  },
  {
    "category": "rushing_and_receiving",
    "rows": [
      {
        "year_id": "2021",
        "age": "23",
        "team": "SFO",
        "pos": "RB",
        "uniform_number": "25",
        "g": "11",
        "gs": "10",
        "rush_att": "207",
        "rush_yds": "963",
        "rush_td": "5",
        "rush_first_down": "47",
        "rush_success": "49.8",
        "rush_long": "39",
        "rush_yds_per_att": "4.7",
        "rush_yds_per_g": "87.5",
        "rush_att_per_g": "18.8",
        "targets": "20",
        "rec": "19",
        "rec_yds": "137",
        "rec_yds_per_rec": "7.2",
        "rec_td": "1",
        "rec_first_down": "6",
        "rec_success": "50.0",
        "rec_long": "14",
        "rec_per_g": "1.7",
        "rec_yds_per_g": "12.5",
        "catch_pct": "95.0%",
        "rec_yds_per_tgt": "6.9",
        "touches": "226",
        "yds_per_touch": "4.9",
        "yds_from_scrimmage": "1100",
        "rush_receive_td": "6",
        "fumbles": "0",
        "av": "7"
      },
      {
        "year_id": "2022",
        "age": "24",
        "team": "SFO",
        "pos": "RB",
        "uniform_number": "25",
        "g": "5",
        "gs": "1",
        "rush_att": "45",
        "rush_yds": "279",
        "rush_td": "2",
        "rush_first_down": "15",
        "rush_success": "71.1",
        "rush_long": "37",
        "rush_yds_per_att": "6.2",
        "rush_yds_per_g": "55.8",
        "rush_att_per_g": "9.0",
        "targets": "4",
        "rec": "3",
        "rec_yds": "7",
        "rec_yds_per_rec": "2.3",
        "rec_td": "0",
        "rec_first_down": "0",
        "rec_success": "50.0",
        "rec_long": "5",
        "rec_per_g": "0.6",
        "rec_yds_per_g": "1.4",
        "catch_pct": "75.0%",
        "rec_yds_per_tgt": "1.8",
        "touches": "48",
        "yds_per_touch": "6.0",
        "yds_from_scrimmage": "286",
        "rush_receive_td": "2",
        "fumbles": "0",
        "av": "2"
      },
      {
        "year_id": "2023",
        "age": "25",
        "team": "SFO",
        "pos": "RB",
        "uniform_number": "25",
        "g": "11",
        "gs": "1",
        "rush_att": "75",
        "rush_yds": "281",
        "rush_td": "2",
        "rush_first_down": "14",
        "rush_success": "48.0",
        "rush_long": "18",
        "rush_yds_per_att": "3.7",
        "rush_yds_per_g": "25.5",
        "rush_att_per_g": "6.8",
        "targets": "8",
        "rec": "6",
        "rec_yds": "14",
        "rec_yds_per_rec": "2.3",
        "rec_td": "0",
        "rec_first_down": "2",
        "rec_success": "37.5",
        "rec_long": "9",
        "rec_per_g": "0.5",
        "rec_yds_per_g": "1.3",
        "catch_pct": "75.0%",
        "rec_yds_per_tgt": "1.8",
        "touches": "81",
        "yds_per_touch": "3.6",
        "yds_from_scrimmage": "295",
        "rush_receive_td": "2",
        "fumbles": "0",
        "av": "2"
      }
    ]
  },
  {
    "category": "defense",
    "rows": []
  },
  {
    "category": "punting",
    "rows": []
  },
  {
    "category": "returns",
    "rows": []
  },
  {
    "category": "scoring",
    "rows": [
      {
        "year_id": "2021",
        "age": "23",
        "team": "SFO",
        "pos": "RB",
        "uniform_number": "25",
        "g": "11",
        "gs": "10",
        "rushtd": "5",
        "rectd": "1",
        "prtd": "",
        "krtd": "",
        "frtd": "",
        "ditd": "",
        "otd": "",
        "alltd": "6",
        "two_pt_md": "",
        "two_pt_att": "",
        "def_two_pt": "0",
        "xpm": "",
        "xpa": "",
        "fgm": "",
        "fga": "",
        "safety_md": "",
        "scoring": "36",
        "points_per_g": "3.3"
      },
      {
        "year_id": "2022",
        "age": "24",
        "team": "SFO",
        "pos": "RB",
        "uniform_number": "25",
        "g": "5",
        "gs": "1",
        "rushtd": "2",
        "rectd": "",
        "prtd": "",
        "krtd": "",
        "frtd": "",
        "ditd": "",
        "otd": "",
        "alltd": "2",
        "two_pt_md": "",
        "two_pt_att": "",
        "def_two_pt": "0",
        "xpm": "",
        "xpa": "",
        "fgm": "",
        "fga": "",
        "safety_md": "",
        "scoring": "12",
        "points_per_g": "2.4"
      },
      {
        "year_id": "2023",
        "age": "25",
        "team": "SFO",
        "pos": "RB",
        "uniform_number": "25",
        "g": "11",
        "gs": "1",
        "rushtd": "2",
        "rectd": "",
        "prtd": "",
        "krtd": "",
        "frtd": "",
        "ditd": "",
        "otd": "",
        "alltd": "2",
        "two_pt_md": "",
        "two_pt_att": "",
        "def_two_pt": "0",
        "xpm": "",
        "xpa": "",
        "fgm": "",
        "fga": "",
        "safety_md": "",
        "scoring": "12",
        "points_per_g": "1.1"
      }
    ]
  },
  {
    "category": "snap_counts",
    "rows": [
      {
        "year_id": "2021",
        "age": "23",
        "team": "SFO",
        "pos": "RB",
        "uniform_number": "25",
        "g": "11",
        "gs": "10",
        "offense": "441",
        "off_pct": "64%",
        "defense": "0",
        "def_pct": "0%",
        "special_teams": "3",
        "st_pct": "1%"
      },
      {
        "year_id": "2022",
        "age": "24",
        "team": "SFO",
        "pos": "RB",
        "uniform_number": "25",
        "g": "5",
        "gs": "1",
        "offense": "80",
        "off_pct": "24%",
        "defense": "0",
        "def_pct": "0%",
        "special_teams": "0",
        "st_pct": "0%"
      },
      {
        "year_id": "2023",
        "age": "25",
        "team": "SFO",
        "pos": "RB",
        "uniform_number": "25",
        "g": "11",
        "gs": "1",
        "offense": "161",
        "off_pct": "23%",
        "defense": "0",
        "def_pct": "0%",
        "special_teams": "0",
        "st_pct": "0%"
      }
    ]
  }
]