[
  {
    "category": "passing",
    "rows": []
  },
  {
    "category": "advanced_air_yards",
    "rows": []
  },
  {
    "category": "advanced_accuracy",
    "rows": []
  },
  {
    "category": "advanced_pressure",
    "rows": []
  },
  {
    "category": "advanced_play_tape",
    "rows": []
  },
  {
    "category": "passing_advanced",
    "rows": []
  },
  {
    "category": "fantasy",
    "rows": []
  },
  {
    "category": "detailed_receiving_and_rushing",
    "rows": []
  },
  {
    "category": "receiving_and_rushing",
    "rows": []
  },
  {
    "category": "rushing_and_receiving",
    "rows": []
  },
  {
    "category": "detailed_rushing_and_receiving",
    "rows": []
  },
  {
    "category": "defense",
    "rows": [
      {
        "year_id": "2019",
        "age": "21",
        "team": "CIN",
        "pos": "LG",
        "uniform_number": "60",
        "g": "13",
        "gs": "9",
        "def_int": "",
        "def_int_yds": "",
        "def_int_td": "0",
        "def_int_long": "",
        "pass_defended": "",
        "fumbles_forced": "0",
        "fumbles": "0",
        "fumbles_rec": "1",
        "fumbles_rec_yds": "0",
        "fumbles_rec_td": "0",
        "sacks": "0.0",
        "tackles_combined": "",
        "tackles_solo": "",
        "tackles_assists": "",
        "tackles_loss": "",
        "qb_hits": "",
        "safety_md": "",
        "av": "4"
      },
      {
        "year_id": "2020",
        "age": "22",
        "team": "CIN",
        "pos": "LG",
        "uniform_number": "60",
        "g": "14",
        "gs": "10",
        "def_int": "",
        "def_int_yds": "",
        "def_int_td": "0",
        "def_int_long": "",
        "pass_defended": "",
        "fumbles_forced": "0",
        "fumbles": "",
        "fumbles_rec": "",
        "fumbles_rec_yds": "",
        "fumbles_rec_td": "",
        "sacks": "0.0",
        "tackles_combined": "",
        "tackles_solo": "",
        "tackles_assists": "",
        "tackles_loss": "",
        "qb_hits": "",
        "safety_md": "",
        "av": "4"
      },
      {
        "year_id": "2021",
        "age": "23",
        "team": "CAR",
        "pos": "LG",
        "uniform_number": "73",
        "g": "11",
        "gs": "10",
        "def_int": "",
        "def_int_yds": "",
        "def_int_td": "0",
        "def_int_long": "",
        "pass_defended": "",
        "fumbles_forced": "0",
        "fumbles": "0",
        "fumbles_rec": "0",
        "fumbles_rec_yds": "0",
        "fumbles_rec_td": "0",
        "sacks": "0.0",
        "tackles_combined": "2",
        "tackles_solo": "2",
        "tackles_assists": "0",
        "tackles_loss": "0",
        "qb_hits": "0",
        "safety_md": "",
        "av": "3"
      },
      {
        "year_id": "2022",
        "age": "24",
        "team": "CAR",
        "pos": "G",
        "uniform_number": "73",
        "g": "17",
        "gs": "0",
        "def_int": "",
        "def_int_yds": "",
        "def_int_td": "0",
        "def_int_long": "",
        "pass_defended": "",
        "fumbles_forced": "0",
        "fumbles": "0",
        "fumbles_rec": "1",
        "fumbles_rec_yds": "0",
        "fumbles_rec_td": "1",
        "sacks": "0.0",
        "tackles_combined": "",
        "tackles_solo": "",
        "tackles_assists": "",
        "tackles_loss": "",
        "qb_hits": "",
        "safety_md": "",
        "av": "1"
      },
      {
        "year_id": "2024",
        "age": "26",
        "team": "NWE",
        "pos": "G",
        "uniform_number": "74",
        "g": "2",
        "gs": "2",
        "def_int": "",
        "def_int_yds": "",
        "def_int_td": "0",
        "def_int_long": "",
        "pass_defended": "",
        "fumbles_forced": "0",
        "fumbles": "0",
        "fumbles_rec": "0",
        "fumbles_rec_yds": "0",
        "fumbles_rec_td": "0",
        "sacks": "0.0",
        "tackles_combined": "",
        "tackles_solo": "",
        "tackles_assists": "",
        "tackles_loss": "",
        "qb_hits": "",
        "safety_md": "",
        "av": ""
      }
    ]
  },
  {
    "category": "punting",
    "rows": []
  },
  {
    "category": "returns",
    "rows": []
  },
  {
    "category": "scoring",
    "rows": [
      {
        "year_id": "2022",
        "age": "24",
        "team": "CAR",
        "pos": "G",
        "uniform_number": "73",
        "g": "17",
        "gs": "0",
        "rushtd": "",
        "rectd": "",
        "prtd": "",
        "krtd": "",
        "frtd": "1",
        "ditd": "",
        "otd": "",
        "alltd": "1",
        "two_pt_md": "",
        "two_pt_att": "",
        "def_two_pt": "0",
        "xpm": "",
        "xpa": "",
        "fgm": "",
        "fga": "",
        "safety_md": "",
        "scoring": "6",
        "points_per_g": "0.4"
      }
    ]
  },
  {
    "category": "snap_counts",
    "rows": [
      {
        "year_id": "2019",
        "age": "21",
        "team": "CIN",
        "pos": "LG",
        "uniform_number": "60",
        "g": "13",
        "gs": "9",
        "offense": "648",
        "off_pct": "71%",
        "defense": "0",
        "def_pct": "0%",
        "special_teams": "32",
        "st_pct": "9%"
      },
      {
        "year_id": "2020",
        "age": "22",
        "team": "CIN",
        "pos": "LG",
        "uniform_number": "60",
        "g": "14",
        "gs": "10",
        "offense": "730",
        "off_pct": "78%",
        "defense": "0",
        "def_pct": "0%",
        "special_teams": "61",
        "st_pct": "15%"
      },
      {
        "year_id": "2021",
        "age": "23",
        "team": "CAR",
        "pos": "LG",
        "uniform_number": "73",
        "g": "11",
        "gs": "10",
        "offense": "703",
        "off_pct": "96%",
        "defense": "0",
        "def_pct": "0%",
        "special_teams": "25",
        "st_pct": "9%"
      },
      {
        "year_id": "2022",
        "age": "24",
        "team": "CAR",
        "pos": "G",
        "uniform_number": "73",
        "g": "17",
        "gs": "0",
        "offense": "54",
        "off_pct": "5%",
        "defense": "0",
        "def_pct": "0%",
        "special_teams": "67",
        "st_pct": "14%"
      },
      {
        "year_id": "2024",
        "age": "26",
        "team": "NWE",
        "pos": "G",
        "uniform_number": "74",
        "g": "2",
        "gs": "2",
        "offense": "133",
        "off_pct": "100%",
        "defense": "0",
        "def_pct": "0%",
        "special_teams": "9",
        "st_pct": "17%"
      }
    ]
  },
  {
    "name": "Michael Jordan",
    "id": "JordMi01",
    "team": "NE",
    "age": "26",
    "position": "G",
    "weight": "315",
    "height": "6-6",
    "college": "Ohio St.",
    "experience": "5",
    "href": "https://www.pro-football-reference.com/players/J/JordMi01.htm"
  }
]