[
  {
    "category": "fantasy",
    "rows": [
      {
        "year_id": "2017",
        "age": "24",
        "g": "1",
        "fantasy_pos": "QB",
        "fantasy_points": "1",
        "vbd": "",
        "fantasy_rank_pos": "65",
        "fantasy_rank_overall": "",
        "games": "All 2017 Games"
      },
      {
        "year_id": "2018",
        "age": "25",
        "g": "6",
        "fantasy_pos": "QB",
        "fantasy_points": "14",
        "vbd": "",
        "fantasy_rank_pos": "50",
        "fantasy_rank_overall": "",
        "games": "All 2018 Games"
      },
      {
        "year_id": "2020",
        "age": "27",
        "g": "1",
        "fantasy_pos": "QB",
        "fantasy_points": "12",
        "vbd": "",
        "fantasy_rank_pos": "57",
        "fantasy_rank_overall": "",
        "games": "All 2020 Games"
      },
      {
        "year_id": "2021",
        "age": "28",
        "g": "16",
        "fantasy_pos": "QB",
        "fantasy_points": "222",
        "vbd": "",
        "fantasy_rank_pos": "20",
        "fantasy_rank_overall": "",
        "games": "All 2021 Games"
      },
      {
        "year_id": "2022",
        "age": "29",
        "g": "9",
        "fantasy_pos": "QB",
        "fantasy_points": "116",
        "vbd": "",
        "fantasy_rank_pos": "30",
        "fantasy_rank_overall": "",
        "games": "All 2022 Games"
      },
      {
        "year_id": "2023",
        "age": "30",
        "g": "5",
        "fantasy_pos": "QB",
        "fantasy_points": "66",
        "vbd": "",
        "fantasy_rank_pos": "42",
        "fantasy_rank_overall": "",
        "games": "All 2023 Games"
      }
    ]
  },
  {
    "category": "detailed_rushing_and_receiving",
    "rows": [
      {
        "year_id": "2018",
        "age": "25",
        "team": "CAR",
        "pos": "QB",
        "uniform_number": "6",
        "g": "6",
        "gs": "1",
        "rush_att": "5",
        "rush_yds": "31",
        "rush_first_down": "2",
        "rush_yds_before_contact": "31",
        "rush_yds_bc_per_rush": "6.2",
        "rush_yac": "0",
        "rush_yac_per_rush": "0.0",
        "rush_broken_tackles": "0",
        "rush_broken_tackles_per_rush": "",
        "targets": "0",
        "rec": "0",
        "rec_yds": "0",
        "rec_first_down": "0",
        "rec_air_yds": "0",
        "rec_air_yds_per_rec": "",
        "rec_yac": "0",
        "rec_yac_per_rec": "",
        "rec_adot": "",
        "rec_broken_tackles": "0",
        "rec_broken_tackles_per_rec": "",
        "rec_drops": "0",
        "rec_drop_pct": "0.0",
        "rec_target_int": "0",
        "rec_pass_rating": ""
      },
      {
        "year_id": "2020",
        "age": "27",
        "team": "WAS",
        "pos": "QB",
        "uniform_number": "4",
        "g": "1",
        "gs": "0",
        "rush_att": "3",
        "rush_yds": "22",
        "rush_first_down": "2",
        "rush_yds_before_contact": "22",
        "rush_yds_bc_per_rush": "7.3",
        "rush_yac": "0",
        "rush_yac_per_rush": "0.0",
        "rush_broken_tackles": "0",
        "rush_broken_tackles_per_rush": "",
        "targets": "0",
        "rec": "0",
        "rec_yds": "0",
        "rec_first_down": "0",
        "rec_air_yds": "0",
        "rec_air_yds_per_rec": "",
        "rec_yac": "0",
        "rec_yac_per_rec": "",
        "rec_adot": "",
        "rec_broken_tackles": "0",
        "rec_broken_tackles_per_rec": "",
        "rec_drops": "0",
        "rec_drop_pct": "0.0",
        "rec_target_int": "0",
        "rec_pass_rating": ""
      },
      {
        "year_id": "2021",
        "age": "28",
        "team": "WAS",
        "pos": "QB",
        "uniform_number": "4",
        "g": "16",
        "gs": "15",
        "rush_att": "60",
        "rush_yds": "313",
        "rush_first_down": "20",
        "rush_yds_before_contact": "278",
        "rush_yds_bc_per_rush": "4.6",
        "rush_yac": "35",
        "rush_yac_per_rush": "0.6",
        "rush_broken_tackles": "1",
        "rush_broken_tackles_per_rush": "60.0",
        "targets": "1",
        "rec": "1",
        "rec_yds": "-2",
        "rec_first_down": "0",
        "rec_air_yds": "-4",
        "rec_air_yds_per_rec": "-4.0",
        "rec_yac": "2",
        "rec_yac_per_rec": "2.0",
        "rec_adot": "-4.0",
        "rec_broken_tackles": "0",
        "rec_broken_tackles_per_rec": "",
        "rec_drops": "0",
        "rec_drop_pct": "0.0",
        "rec_target_int": "0",
        "rec_pass_rating": "79.2"
      },
      {
        "year_id": "2022",
        "age": "29",
        "team": "WAS",
        "pos": "QB",
        "uniform_number": "4",
        "g": "9",
        "gs": "9",
        "rush_att": "28",
        "rush_yds": "96",
        "rush_first_down": "6",
        "rush_yds_before_contact": "71",
        "rush_yds_bc_per_rush": "2.5",
        "rush_yac": "25",
        "rush_yac_per_rush": "0.9",
        "rush_broken_tackles": "1",
        "rush_broken_tackles_per_rush": "28.0",
        "targets": "0",
        "rec": "0",
        "rec_yds": "0",
        "rec_first_down": "0",
        "rec_air_yds": "0",
        "rec_air_yds_per_rec": "",
        "rec_yac": "0",
        "rec_yac_per_rec": "",
        "rec_adot": "",
        "rec_broken_tackles": "0",
        "rec_broken_tackles_per_rec": "",
        "rec_drops": "0",
        "rec_drop_pct": "0.0",
        "rec_target_int": "0",
        "rec_pass_rating": ""
      },
      {
        "year_id": "2023",
        "age": "30",
        "team": "ATL",
        "pos": "QB",
        "uniform_number": "4",
        "g": "5",
        "gs": "4",
        "rush_att": "15",
        "rush_yds": "124",
        "rush_first_down": "5",
        "rush_yds_before_contact": "118",
        "rush_yds_bc_per_rush": "7.9",
        "rush_yac": "6",
        "rush_yac_per_rush": "0.4",
        "rush_broken_tackles": "0",
        "rush_broken_tackles_per_rush": "",
        "targets": "0",
        "rec": "0",
        "rec_yds": "0",
        "rec_first_down": "0",
        "rec_air_yds": "0",
        "rec_air_yds_per_rec": "",
        "rec_yac": "0",
        "rec_yac_per_rec": "",
        "rec_adot": "",
        "rec_broken_tackles": "0",
        "rec_broken_tackles_per_rec": "",
        "rec_drops": "0",
        "rec_drop_pct": "0.0",
        "rec_target_int": "0",
        "rec_pass_rating": ""
      }
    ]
  },
  {
    "category": "passing",
    "rows": [
      {
        "year_id": "2017",
        "age": "24",
        "team_name_abbr": "HOU",
        "comp_name_abbr": "NFL",
        "pos": "QB",
        "games": "1",
        "games_started": "0",
        "qb_rec": "",
        "pass_cmp": "1",
        "pass_att": "1",
        "pass_cmp_pct": "100.0",
        "pass_yds": "10",
        "pass_td": "0",
        "pass_td_pct": "0.0",
        "pass_int": "0",
        "pass_int_pct": "0.0",
        "pass_first_down": "1",
        "pass_success": "50.0",
        "pass_long": "10",
        "pass_yds_per_att": "10.0",
        "pass_adj_yds_per_att": "10.00",
        "pass_yds_per_cmp": "10.0",
        "pass_yds_per_g": "10.0",
        "pass_rating": "108.3",
        "qbr": "1.3",
        "pass_sacked": "1",
        "pass_sacked_yds": "16",
        "pass_sacked_pct": "50.00",
        "pass_net_yds_per_att": "-3.00",
        "pass_adj_net_yds_per_att": "-3.00",
        "comebacks": "0",
        "gwd": "0",
        "av": "0",
        "awards": ""
      },
      {
        "year_id": "2018",
        "age": "25",
        "team_name_abbr": "CAR",
        "comp_name_abbr": "NFL",
        "pos": "QB",
        "games": "6",
        "games_started": "1",
        "qb_rec": "0-1-0",
        "pass_cmp": "35",
        "pass_att": "57",
        "pass_cmp_pct": "61.4",
        "pass_yds": "320",
        "pass_td": "1",
        "pass_td_pct": "1.8",
        "pass_int": "3",
        "pass_int_pct": "5.3",
        "pass_first_down": "19",
        "pass_success": "40.7",
        "pass_long": "33",
        "pass_yds_per_att": "5.6",
        "pass_adj_yds_per_att": "3.60",
        "pass_yds_per_cmp": "9.1",
        "pass_yds_per_g": "53.3",
        "pass_rating": "60.6",
        "qbr": "18.3",
        "pass_sacked": "2",
        "pass_sacked_yds": "17",
        "pass_sacked_pct": "3.39",
        "pass_net_yds_per_att": "5.14",
        "pass_adj_net_yds_per_att": "3.19",
        "comebacks": "0",
        "gwd": "0",
        "av": "1",
        "awards": ""
      },
      {
        "year_id": "",
        "age": "",
        "team_name_abbr": "",
        "comp_name_abbr": "",
        "pos": "",
        "games": "",
        "games_started": "",
        "qb_rec": "",
        "pass_cmp": "",
        "pass_att": "",
        "pass_cmp_pct": "",
        "pass_yds": "",
        "pass_td": "",
        "pass_td_pct": "",
        "pass_int": "",
        "pass_int_pct": "",
        "pass_first_down": "",
        "pass_success": "",
        "pass_long": "",
        "pass_yds_per_att": "",
        "pass_adj_yds_per_att": "",
        "pass_yds_per_cmp": "",
        "pass_yds_per_g": "",
        "pass_rating": "",
        "qbr": "",
        "pass_sacked": "",
        "pass_sacked_yds": "",
        "pass_sacked_pct": "",
        "pass_net_yds_per_att": "",
        "pass_adj_net_yds_per_att": "",
        "comebacks": "",
        "gwd": "",
        "av": "",
        "awards": ""
      },
      {
        "year_id": "2020",
        "age": "27",
        "team_name_abbr": "WAS",
        "comp_name_abbr": "NFL",
        "pos": "QB",
        "games": "1",
        "games_started": "0",
        "qb_rec": "",
        "pass_cmp": "12",
        "pass_att": "19",
        "pass_cmp_pct": "63.2",
        "pass_yds": "137",
        "pass_td": "1",
        "pass_td_pct": "5.3",
        "pass_int": "0",
        "pass_int_pct": "0.0",
        "pass_first_down": "6",
        "pass_success": "55.0",
        "pass_long": "29",
        "pass_yds_per_att": "7.2",
        "pass_adj_yds_per_att": "8.26",
        "pass_yds_per_cmp": "11.4",
        "pass_yds_per_g": "137.0",
        "pass_rating": "102.3",
        "qbr": "40.7",
        "pass_sacked": "1",
        "pass_sacked_yds": "7",
        "pass_sacked_pct": "5.00",
        "pass_net_yds_per_att": "6.50",
        "pass_adj_net_yds_per_att": "7.50",
        "comebacks": "0",
        "gwd": "0",
        "av": "0",
        "awards": ""
      },
      {
        "year_id": "2021",
        "age": "28",
        "team_name_abbr": "WAS",
        "comp_name_abbr": "NFL",
        "pos": "QB",
        "games": "16",
        "games_started": "15",
        "qb_rec": "7-8-0",
        "pass_cmp": "321",
        "pass_att": "494",
        "pass_cmp_pct": "65.0",
        "pass_yds": "3419",
        "pass_td": "20",
        "pass_td_pct": "4.0",
        "pass_int": "15",
        "pass_int_pct": "3.0",
        "pass_first_down": "167",
        "pass_success": "44.9",
        "pass_long": "73",
        "pass_yds_per_att": "6.9",
        "pass_adj_yds_per_att": "6.36",
        "pass_yds_per_cmp": "10.7",
        "pass_yds_per_g": "213.7",
        "pass_rating": "85.9",
        "qbr": "45.8",
        "pass_sacked": "38",
        "pass_sacked_yds": "278",
        "pass_sacked_pct": "7.14",
        "pass_net_yds_per_att": "5.90",
        "pass_adj_net_yds_per_att": "5.39",
        "comebacks": "3",
        "gwd": "4",
        "av": "11",
        "awards": ""
      },
      {
        "year_id": "2022",
        "age": "29",
        "team_name_abbr": "WAS",
        "comp_name_abbr": "NFL",
        "pos": "QB",
        "games": "9",
        "games_started": "9",
        "qb_rec": "5-3-1",
        "pass_cmp": "161",
        "pass_att": "259",
        "pass_cmp_pct": "62.2",
        "pass_yds": "1859",
        "pass_td": "12",
        "pass_td_pct": "4.6",
        "pass_int": "6",
        "pass_int_pct": "2.3",
        "pass_first_down": "93",
        "pass_success": "43.2",
        "pass_long": "61",
        "pass_yds_per_att": "7.2",
        "pass_adj_yds_per_att": "7.06",
        "pass_yds_per_cmp": "11.5",
        "pass_yds_per_g": "206.6",
        "pass_rating": "89.6",
        "qbr": "46.5",
        "pass_sacked": "19",
        "pass_sacked_yds": "141",
        "pass_sacked_pct": "6.83",
        "pass_net_yds_per_att": "6.18",
        "pass_adj_net_yds_per_att": "6.07",
        "comebacks": "2",
        "gwd": "1",
        "av": "6",
        "awards": ""
      },
      {
        "year_id": "2023",
        "age": "30",
        "team_name_abbr": "ATL",
        "comp_name_abbr": "NFL",
        "pos": "QB",
        "games": "5",
        "games_started": "4",
        "qb_rec": "1-3-0",
        "pass_cmp": "74",
        "pass_att": "136",
        "pass_cmp_pct": "54.4",
        "pass_yds": "890",
        "pass_td": "5",
        "pass_td_pct": "3.7",
        "pass_int": "4",
        "pass_int_pct": "2.9",
        "pass_first_down": "41",
        "pass_success": "40.3",
        "pass_long": "75",
        "pass_yds_per_att": "6.5",
        "pass_adj_yds_per_att": "5.96",
        "pass_yds_per_cmp": "12.0",
        "pass_yds_per_g": "178.0",
        "pass_rating": "74.7",
        "qbr": "47.7",
        "pass_sacked": "8",
        "pass_sacked_yds": "47",
        "pass_sacked_pct": "5.56",
        "pass_net_yds_per_att": "5.85",
        "pass_adj_net_yds_per_att": "5.30",
        "comebacks": "0",
        "gwd": "0",
        "av": "3",
        "awards": ""
      }
    ]
  },
  {
    "category": "advanced_air_yards",
    "rows": [
      {
        "year_id": "2018",
        "age": "25",
        "team": "CAR",
        "pos": "QB",
        "uniform_number": "6",
        "g": "6",
        "gs": "1",
        "pass_cmp": "35",
        "pass_att": "57",
        "pass_yds": "320",
        "pass_target_yds": "512",
        "pass_tgt_yds_per_att": "9.0",
        "pass_air_yds": "173",
        "pass_air_yds_per_cmp": "4.9",
        "pass_air_yds_per_att": "3.0",
        "pass_yac": "147",
        "pass_yac_per_cmp": "4.2"
      },
      {
        "year_id": "2020",
        "age": "27",
        "team": "WAS",
        "pos": "QB",
        "uniform_number": "4",
        "g": "1",
        "gs": "0",
        "pass_cmp": "12",
        "pass_att": "19",
        "pass_yds": "137",
        "pass_target_yds": "255",
        "pass_tgt_yds_per_att": "13.4",
        "pass_air_yds": "88",
        "pass_air_yds_per_cmp": "7.3",
        "pass_air_yds_per_att": "4.6",
        "pass_yac": "49",
        "pass_yac_per_cmp": "4.1"
      },
      {
        "year_id": "2021",
        "age": "28",
        "team": "WAS",
        "pos": "QB",
        "uniform_number": "4",
        "g": "16",
        "gs": "15",
        "pass_cmp": "321",
        "pass_att": "494",
        "pass_yds": "3419",
        "pass_target_yds": "3762",
        "pass_tgt_yds_per_att": "7.6",
        "pass_air_yds": "1655",
        "pass_air_yds_per_cmp": "5.2",
        "pass_air_yds_per_att": "3.4",
        "pass_yac": "1764",
        "pass_yac_per_cmp": "5.5"
      },
      {
        "year_id": "2022",
        "age": "29",
        "team": "WAS",
        "pos": "QB",
        "uniform_number": "4",
        "g": "9",
        "gs": "9",
        "pass_cmp": "161",
        "pass_att": "259",
        "pass_yds": "1859",
        "pass_target_yds": "2099",
        "pass_tgt_yds_per_att": "8.1",
        "pass_air_yds": "1075",
        "pass_air_yds_per_cmp": "6.7",
        "pass_air_yds_per_att": "4.2",
        "pass_yac": "784",
        "pass_yac_per_cmp": "4.9"
      },
      {
        "year_id": "2023",
        "age": "30",
        "team": "ATL",
        "pos": "QB",
        "uniform_number": "4",
        "g": "5",
        "gs": "4",
        "pass_cmp": "74",
        "pass_att": "136",
        "pass_yds": "890",
        "pass_target_yds": "1137",
        "pass_tgt_yds_per_att": "8.4",
        "pass_air_yds": "383",
        "pass_air_yds_per_cmp": "5.2",
        "pass_air_yds_per_att": "2.8",
        "pass_yac": "507",
        "pass_yac_per_cmp": "6.9"
      }
    ]
  },
  {
    "category": "advanced_accuracy",
    "rows": [
      {
        "year_id": "2018",
        "age": "25",
        "team": "CAR",
        "pos": "QB",
        "uniform_number": "6",
        "g": "6",
        "gs": "1",
        "pass_cmp": "35",
        "pass_att": "57",
        "pass_yds": "320",
        "pass_batted_passes": "0",
        "pass_throwaways": "3",
        "pass_spikes": "1",
        "pass_drops": "0",
        "pass_drop_pct": "0.0%",
        "pass_poor_throws": "14",
        "pass_poor_throw_pct": "26.4%",
        "pass_on_target": "",
        "pass_on_target_pct": ""
      },
      {
        "year_id": "2020",
        "age": "27",
        "team": "WAS",
        "pos": "QB",
        "uniform_number": "4",
        "g": "1",
        "gs": "0",
        "pass_cmp": "12",
        "pass_att": "19",
        "pass_yds": "137",
        "pass_batted_passes": "0",
        "pass_throwaways": "0",
        "pass_spikes": "0",
        "pass_drops": "1",
        "pass_drop_pct": "5.3%",
        "pass_poor_throws": "4",
        "pass_poor_throw_pct": "21.1%",
        "pass_on_target": "13",
        "pass_on_target_pct": "68.4%"
      },
      {
        "year_id": "2021",
        "age": "28",
        "team": "WAS",
        "pos": "QB",
        "uniform_number": "4",
        "g": "16",
        "gs": "15",
        "pass_cmp": "321",
        "pass_att": "494",
        "pass_yds": "3419",
        "pass_batted_passes": "9",
        "pass_throwaways": "8",
        "pass_spikes": "3",
        "pass_drops": "18",
        "pass_drop_pct": "3.7%",
        "pass_poor_throws": "80",
        "pass_poor_throw_pct": "16.6%",
        "pass_on_target": "365",
        "pass_on_target_pct": "75.6%"
      },
      {
        "year_id": "2022",
        "age": "29",
        "team": "WAS",
        "pos": "QB",
        "uniform_number": "4",
        "g": "9",
        "gs": "9",
        "pass_cmp": "161",
        "pass_att": "259",
        "pass_yds": "1859",
        "pass_batted_passes": "7",
        "pass_throwaways": "14",
        "pass_spikes": "2",
        "pass_drops": "6",
        "pass_drop_pct": "2.5%",
        "pass_poor_throws": "44",
        "pass_poor_throw_pct": "18.1%",
        "pass_on_target": "177",
        "pass_on_target_pct": "72.8%"
      },
      {
        "year_id": "2023",
        "age": "30",
        "team": "ATL",
        "pos": "QB",
        "uniform_number": "4",
        "g": "5",
        "gs": "4",
        "pass_cmp": "74",
        "pass_att": "136",
        "pass_yds": "890",
        "pass_batted_passes": "2",
        "pass_throwaways": "6",
        "pass_spikes": "2",
        "pass_drops": "8",
        "pass_drop_pct": "6.3%",
        "pass_poor_throws": "31",
        "pass_poor_throw_pct": "24.2%",
        "pass_on_target": "89",
        "pass_on_target_pct": "69.5%"
      }
    ]
  },
  {
    "category": "advanced_pressure",
    "rows": [
      {
        "year_id": "2018",
        "age": "25",
        "team": "CAR",
        "pos": "QB",
        "uniform_number": "6",
        "g": "6",
        "gs": "1",
        "pass_cmp": "35",
        "pass_att": "57",
        "pass_yds": "320",
        "pass_sacked": "2",
        "pocket_time": "2.3",
        "pass_blitzed": "17",
        "pass_hurried": "5",
        "pass_hits": "8",
        "pass_pressured": "15",
        "pass_pressured_pct": "24.6%",
        "rush_scrambles": "2",
        "rush_scrambles_yds_per_att": "15.0"
      },
      {
        "year_id": "2020",
        "age": "27",
        "team": "WAS",
        "pos": "QB",
        "uniform_number": "4",
        "g": "1",
        "gs": "0",
        "pass_cmp": "12",
        "pass_att": "19",
        "pass_yds": "137",
        "pass_sacked": "1",
        "pocket_time": "3.0",
        "pass_blitzed": "3",
        "pass_hurried": "1",
        "pass_hits": "1",
        "pass_pressured": "3",
        "pass_pressured_pct": "13.0%",
        "rush_scrambles": "3",
        "rush_scrambles_yds_per_att": "7.3"
      },
      {
        "year_id": "2021",
        "age": "28",
        "team": "WAS",
        "pos": "QB",
        "uniform_number": "4",
        "g": "16",
        "gs": "15",
        "pass_cmp": "321",
        "pass_att": "494",
        "pass_yds": "3419",
        "pass_sacked": "38",
        "pocket_time": "2.6",
        "pass_blitzed": "145",
        "pass_hurried": "55",
        "pass_hits": "47",
        "pass_pressured": "140",
        "pass_pressured_pct": "24.6%",
        "rush_scrambles": "38",
        "rush_scrambles_yds_per_att": "7.1"
      },
      {
        "year_id": "2022",
        "age": "29",
        "team": "WAS",
        "pos": "QB",
        "uniform_number": "4",
        "g": "9",
        "gs": "9",
        "pass_cmp": "161",
        "pass_att": "259",
        "pass_yds": "1859",
        "pass_sacked": "19",
        "pocket_time": "2.5",
        "pass_blitzed": "63",
        "pass_hurried": "22",
        "pass_hits": "40",
        "pass_pressured": "81",
        "pass_pressured_pct": "27.7%",
        "rush_scrambles": "14",
        "rush_scrambles_yds_per_att": "6.5"
      },
      {
        "year_id": "2023",
        "age": "30",
        "team": "ATL",
        "pos": "QB",
        "uniform_number": "4",
        "g": "5",
        "gs": "4",
        "pass_cmp": "74",
        "pass_att": "136",
        "pass_yds": "890",
        "pass_sacked": "8",
        "pocket_time": "2.5",
        "pass_blitzed": "37",
        "pass_hurried": "9",
        "pass_hits": "13",
        "pass_pressured": "30",
        "pass_pressured_pct": "19.1%",
        "rush_scrambles": "13",
        "rush_scrambles_yds_per_att": "9.6"
      }
    ]
  },
  {
    "category": "advanced_play_tape",
    "rows": []
  },
  {
    "category": "passing_advanced",
    "rows": [
      {
        "year_id": "2018",
        "age": "25",
        "team": "CAR",
        "pos": "QB",
        "uniform_number": "6",
        "g": "6",
        "gs": "1",
        "qb_rec": "0-1-0",
        "pass_att": "57",
        "pass_yds_per_att_index": "69",
        "pass_net_yds_per_att_index": "79",
        "pass_adj_yds_per_att_index": "54",
        "pass_adj_net_yds_per_att_index": "61",
        "pass_cmp_perc_index": "92",
        "pass_td_perc_index": "71",
        "pass_int_perc_index": "52",
        "pass_sacked_perc_index": "124",
        "pass_rating_index": "61"
      },
      {
        "year_id": "2021",
        "age": "28",
        "team": "WAS",
        "pos": "QB",
        "uniform_number": "4",
        "g": "16",
        "gs": "15",
        "qb_rec": "7-8-0",
        "pass_att": "494",
        "pass_yds_per_att_index": "96",
        "pass_net_yds_per_att_index": "93",
        "pass_adj_yds_per_att_index": "91",
        "pass_adj_net_yds_per_att_index": "90",
        "pass_cmp_perc_index": "100",
        "pass_td_perc_index": "95",
        "pass_int_perc_index": "84",
        "pass_sacked_perc_index": "93",
        "pass_rating_index": "92"
      },
      {
        "year_id": "2022",
        "age": "29",
        "team": "WAS",
        "pos": "QB",
        "uniform_number": "4",
        "g": "9",
        "gs": "9",
        "qb_rec": "5-3-1",
        "pass_att": "259",
        "pass_yds_per_att_index": "103",
        "pass_net_yds_per_att_index": "100",
        "pass_adj_yds_per_att_index": "103",
        "pass_adj_net_yds_per_att_index": "101",
        "pass_cmp_perc_index": "89",
        "pass_td_perc_index": "104",
        "pass_int_perc_index": "100",
        "pass_sacked_perc_index": "97",
        "pass_rating_index": "99"
      },
      {
        "year_id": "2023",
        "age": "30",
        "team": "ATL",
        "pos": "QB",
        "uniform_number": "4",
        "g": "5",
        "gs": "4",
        "qb_rec": "1-3-0",
        "pass_att": "136",
        "pass_yds_per_att_index": "89",
        "pass_net_yds_per_att_index": "95",
        "pass_adj_yds_per_att_index": "86",
        "pass_adj_net_yds_per_att_index": "91",
        "pass_cmp_perc_index": "52",
        "pass_td_perc_index": "94",
        "pass_int_perc_index": "86",
        "pass_sacked_perc_index": "110",
        "pass_rating_index": "75"
      }
    ]
  },
  {
    "category": "detailed_receiving_and_rushing",
    "rows": []
  },
  {
    "category": "receiving_and_rushing",
    "rows": []
  },
  {
    "category": "rushing_and_receiving",
    "rows": [
      {
        "year_id": "2017",
        "age": "24",
        "team": "HOU",
        "pos": "QB",
        "uniform_number": "8",
        "g": "1",
        "gs": "0",
        "rush_att": "1",
        "rush_yds": "2",
        "rush_td": "0",
        "rush_first_down": "0",
        "rush_success": "0.0",
        "rush_long": "2",
        "rush_yds_per_att": "2.0",
        "rush_yds_per_g": "2.0",
        "rush_att_per_g": "1.0",
        "targets": "",
        "rec": "",
        "rec_yds": "",
        "rec_yds_per_rec": "",
        "rec_td": "0",
        "rec_first_down": "",
        "rec_success": "",
        "rec_long": "",
        "rec_per_g": "",
        "rec_yds_per_g": "",
        "catch_pct": "",
        "rec_yds_per_tgt": "",
        "touches": "1",
        "yds_per_touch": "2.0",
        "yds_from_scrimmage": "2",
        "rush_receive_td": "0",
        "fumbles": "0"
      },
      {
        "year_id": "2018",
        "age": "25",
        "team": "CAR",
        "pos": "QB",
        "uniform_number": "6",
        "g": "6",
        "gs": "1",
        "rush_att": "5",
        "rush_yds": "31",
        "rush_td": "0",
        "rush_first_down": "2",
        "rush_success": "40.0",
        "rush_long": "19",
        "rush_yds_per_att": "6.2",
        "rush_yds_per_g": "5.2",
        "rush_att_per_g": "0.8",
        "targets": "",
        "rec": "",
        "rec_yds": "",
        "rec_yds_per_rec": "",
        "rec_td": "0",
        "rec_first_down": "",
        "rec_success": "",
        "rec_long": "",
        "rec_per_g": "",
        "rec_yds_per_g": "",
        "catch_pct": "",
        "rec_yds_per_tgt": "",
        "touches": "5",
        "yds_per_touch": "6.2",
        "yds_from_scrimmage": "31",
        "rush_receive_td": "0",
        "fumbles": "1"
      },
      {
        "year_id": "2020",
        "age": "27",
        "team": "WAS",
        "pos": "QB",
        "uniform_number": "4",
        "g": "1",
        "gs": "0",
        "rush_att": "3",
        "rush_yds": "22",
        "rush_td": "0",
        "rush_first_down": "2",
        "rush_success": "100.0",
        "rush_long": "12",
        "rush_yds_per_att": "7.3",
        "rush_yds_per_g": "22.0",
        "rush_att_per_g": "3.0",
        "targets": "",
        "rec": "",
        "rec_yds": "",
        "rec_yds_per_rec": "",
        "rec_td": "0",
        "rec_first_down": "",
        "rec_success": "",
        "rec_long": "",
        "rec_per_g": "",
        "rec_yds_per_g": "",
        "catch_pct": "",
        "rec_yds_per_tgt": "",
        "touches": "3",
        "yds_per_touch": "7.3",
        "yds_from_scrimmage": "22",
        "rush_receive_td": "0",
        "fumbles": "0"
      },
      {
        "year_id": "2021",
        "age": "28",
        "team": "WAS",
        "pos": "QB",
        "uniform_number": "4",
        "g": "16",
        "gs": "15",
        "rush_att": "60",
        "rush_yds": "313",
        "rush_td": "1",
        "rush_first_down": "20",
        "rush_success": "46.7",
        "rush_long": "38",
        "rush_yds_per_att": "5.2",
        "rush_yds_per_g": "19.6",
        "rush_att_per_g": "3.8",
        "targets": "1",
        "rec": "1",
        "rec_yds": "-2",
        "rec_yds_per_rec": "-2.0",
        "rec_td": "0",
        "rec_first_down": "0",
        "rec_success": "0.0",
        "rec_long": "-2",
        "rec_per_g": "0.1",
        "rec_yds_per_g": "-0.1",
        "catch_pct": "100.0%",
        "rec_yds_per_tgt": "-2.0",
        "touches": "61",
        "yds_per_touch": "5.1",
        "yds_from_scrimmage": "311",
        "rush_receive_td": "1",
        "fumbles": "7"
      },
      {
        "year_id": "2022",
        "age": "29",
        "team": "WAS",
        "pos": "QB",
        "uniform_number": "4",
        "g": "9",
        "gs": "9",
        "rush_att": "28",
        "rush_yds": "96",
        "rush_td": "1",
        "rush_first_down": "6",
        "rush_success": "46.4",
        "rush_long": "15",
        "rush_yds_per_att": "3.4",
        "rush_yds_per_g": "10.7",
        "rush_att_per_g": "3.1",
        "targets": "",
        "rec": "",
        "rec_yds": "",
        "rec_yds_per_rec": "",
        "rec_td": "0",
        "rec_first_down": "",
        "rec_success": "",
        "rec_long": "",
        "rec_per_g": "",
        "rec_yds_per_g": "",
        "catch_pct": "",
        "rec_yds_per_tgt": "",
        "touches": "28",
        "yds_per_touch": "3.4",
        "yds_from_scrimmage": "96",
        "rush_receive_td": "1",
        "fumbles": "7"
      },
      {
        "year_id": "2023",
        "age": "30",
        "team": "ATL",
        "pos": "QB",
        "uniform_number": "4",
        "g": "5",
        "gs": "4",
        "rush_att": "15",
        "rush_yds": "124",
        "rush_td": "1",
        "rush_first_down": "5",
        "rush_success": "53.3",
        "rush_long": "24",
        "rush_yds_per_att": "8.3",
        "rush_yds_per_g": "24.8",
        "rush_att_per_g": "3.0",
        "targets": "",
        "rec": "",
        "rec_yds": "",
        "rec_yds_per_rec": "",
        "rec_td": "0",
        "rec_first_down": "",
        "rec_success": "",
        "rec_long": "",
        "rec_per_g": "",
        "rec_yds_per_g": "",
        "catch_pct": "",
        "rec_yds_per_tgt": "",
        "touches": "15",
        "yds_per_touch": "8.3",
        "yds_from_scrimmage": "124",
        "rush_receive_td": "1",
        "fumbles": "1"
      }
    ]
  },
  {
    "category": "defense",
    "rows": [
      {
        "year_id": "2018",
        "age": "25",
        "team": "CAR",
        "pos": "QB",
        "uniform_number": "6",
        "g": "6",
        "gs": "1",
        "def_int": "",
        "def_int_yds": "",
        "def_int_td": "0",
        "def_int_long": "",
        "pass_defended": "",
        "fumbles_forced": "0",
        "fumbles": "1",
        "fumbles_rec": "1",
        "fumbles_rec_yds": "0",
        "fumbles_rec_td": "0",
        "sacks": "0.0",
        "tackles_combined": "",
        "tackles_solo": "",
        "tackles_assists": "",
        "tackles_loss": "",
        "qb_hits": "",
        "safety_md": ""
      },
      {
        "year_id": "2021",
        "age": "28",
        "team": "WAS",
        "pos": "QB",
        "uniform_number": "4",
        "g": "16",
        "gs": "15",
        "def_int": "",
        "def_int_yds": "",
        "def_int_td": "0",
        "def_int_long": "",
        "pass_defended": "",
        "fumbles_forced": "0",
        "fumbles": "7",
        "fumbles_rec": "6",
        "fumbles_rec_yds": "1",
        "fumbles_rec_td": "0",
        "sacks": "0.0",
        "tackles_combined": "",
        "tackles_solo": "",
        "tackles_assists": "",
        "tackles_loss": "",
        "qb_hits": "",
        "safety_md": ""
      },
      {
        "year_id": "2022",
        "age": "29",
        "team": "WAS",
        "pos": "QB",
        "uniform_number": "4",
        "g": "9",
        "gs": "9",
        "def_int": "",
        "def_int_yds": "",
        "def_int_td": "0",
        "def_int_long": "",
        "pass_defended": "",
        "fumbles_forced": "1",
        "fumbles": "7",
        "fumbles_rec": "2",
        "fumbles_rec_yds": "-9",
        "fumbles_rec_td": "0",
        "sacks": "0.0",
        "tackles_combined": "",
        "tackles_solo": "",
        "tackles_assists": "",
        "tackles_loss": "",
        "qb_hits": "",
        "safety_md": ""
      },
      {
        "year_id": "2023",
        "age": "30",
        "team": "ATL",
        "pos": "QB",
        "uniform_number": "4",
        "g": "5",
        "gs": "4",
        "def_int": "",
        "def_int_yds": "",
        "def_int_td": "0",
        "def_int_long": "",
        "pass_defended": "",
        "fumbles_forced": "0",
        "fumbles": "1",
        "fumbles_rec": "1",
        "fumbles_rec_yds": "-4",
        "fumbles_rec_td": "0",
        "sacks": "0.0",
        "tackles_combined": "",
        "tackles_solo": "",
        "tackles_assists": "",
        "tackles_loss": "",
        "qb_hits": "",
        "safety_md": ""
      }
    ]
  },
  {
    "category": "punting",
    "rows": []
  },
  {
    "category": "returns",
    "rows": []
  },
  {
    "category": "scoring",
    "rows": [
      {
        "year_id": "2021",
        "age": "28",
        "team": "WAS",
        "pos": "QB",
        "uniform_number": "4",
        "g": "16",
        "gs": "15",
        "rushtd": "1",
        "rectd": "",
        "prtd": "",
        "krtd": "",
        "frtd": "",
        "ditd": "",
        "otd": "",
        "alltd": "1",
        "two_pt_md": "1",
        "two_pt_att": "",
        "def_two_pt": "0",
        "xpm": "",
        "xpa": "",
        "fgm": "",
        "fga": "",
        "safety_md": "",
        "scoring": "8",
        "points_per_g": "0.5"
      },
      {
        "year_id": "2022",
        "age": "29",
        "team": "WAS",
        "pos": "QB",
        "uniform_number": "4",
        "g": "9",
        "gs": "9",
        "rushtd": "1",
        "rectd": "",
        "prtd": "",
        "krtd": "",
        "frtd": "",
        "ditd": "",
        "otd": "",
        "alltd": "1",
        "two_pt_md": "",
        "two_pt_att": "",
        "def_two_pt": "0",
        "xpm": "",
        "xpa": "",
        "fgm": "",
        "fga": "",
        "safety_md": "",
        "scoring": "6",
        "points_per_g": "0.7"
      },
      {
        "year_id": "2023",
        "age": "30",
        "team": "ATL",
        "pos": "QB",
        "uniform_number": "4",
        "g": "5",
        "gs": "4",
        "rushtd": "1",
        "rectd": "",
        "prtd": "",
        "krtd": "",
        "frtd": "",
        "ditd": "",
        "otd": "",
        "alltd": "1",
        "two_pt_md": "",
        "two_pt_att": "",
        "def_two_pt": "0",
        "xpm": "",
        "xpa": "",
        "fgm": "",
        "fga": "",
        "safety_md": "",
        "scoring": "6",
        "points_per_g": "1.2"
      }
    ]
  },
  {
    "category": "snap_counts",
    "rows": [
      {
        "year_id": "2017",
        "age": "24",
        "team": "HOU",
        "pos": "QB",
        "uniform_number": "8",
        "g": "1",
        "gs": "0",
        "offense": "9",
        "off_pct": "16%",
        "defense": "0",
        "def_pct": "0%",
        "special_teams": "0",
        "st_pct": "0%"
      },
      {
        "year_id": "2018",
        "age": "25",
        "team": "CAR",
        "pos": "QB",
        "uniform_number": "6",
        "g": "6",
        "gs": "1",
        "offense": "92",
        "off_pct": "22%",
        "defense": "0",
        "def_pct": "0%",
        "special_teams": "0",
        "st_pct": "0%"
      },
      {
        "year_id": "2020",
        "age": "27",
        "team": "WAS",
        "pos": "QB",
        "uniform_number": "4",
        "g": "1",
        "gs": "0",
        "offense": "25",
        "off_pct": "35%",
        "defense": "0",
        "def_pct": "0%",
        "special_teams": "0",
        "st_pct": "0%"
      },
      {
        "year_id": "2021",
        "age": "28",
        "team": "WAS",
        "pos": "QB",
        "uniform_number": "4",
        "g": "16",
        "gs": "15",
        "offense": "1019",
        "off_pct": "95%",
        "defense": "0",
        "def_pct": "0%",
        "special_teams": "0",
        "st_pct": "0%"
      },
      {
        "year_id": "2022",
        "age": "29",
        "team": "WAS",
        "pos": "QB",
        "uniform_number": "4",
        "g": "9",
        "gs": "9",
        "offense": "614",
        "off_pct": "97%",
        "defense": "0",
        "def_pct": "0%",
        "special_teams": "0",
        "st_pct": "0%"
      },
      {
        "year_id": "2023",
        "age": "30",
        "team": "ATL",
        "pos": "QB",
        "uniform_number": "4",
        "g": "5",
        "gs": "4",
        "offense": "271",
        "off_pct": "82%",
        "defense": "0",
        "def_pct": "0%",
        "special_teams": "0",
        "st_pct": "0%"
      }
    ]
  },
  {
    "name": "Taylor Heinicke",
    "age": "31",
    "position": "QB",
    "weight": "210",
    "height": "6-1",
    "college": "Old Dominion",
    "experience": "7"
  }
]